{
  "execution_start": "2025-08-17T02:28:32.433987",
  "milestones": [
    {
      "id": "T1_M1_ACCOUNT_SETUP",
      "track": "TRACK_1",
      "description": "QuantConnect account creation + verification",
      "planned_start": "2025-08-17 02:28:32.433987",
      "planned_duration": 30,
      "actual_start": "2025-08-17 02:28:32.434988",
      "actual_end": null,
      "status": "IN_PROGRESS",
      "success_criteria": [
        "QuantConnect account active",
        "Algorithm Lab accessible",
        "Paper trading capability confirmed"
      ],
      "actual_results": {},
      "issues": [],
      "cost_impact": 0.0
    },
    {
      "id": "T1_M2_ALGORITHM_UPLOAD",
      "track": "TRACK_1",
      "description": "Algorithm upload + compilation",
      "planned_start": "2025-08-17 02:58:32.433987",
      "planned_duration": 45,
      "actual_start": null,
      "actual_end": null,
      "status": "PENDING",
      "success_criteria": [
        "Algorithm code uploaded completely",
        "Compilation successful - no errors",
        "Optimized parameters verified (5/35 MA, 0.5%)"
      ],
      "actual_results": {},
      "issues": [],
      "cost_impact": 0.0
    },
    {
      "id": "T1_M3_BACKTEST_VALIDATION",
      "track": "TRACK_1",
      "description": "Backtesting execution + results validation",
      "planned_start": "2025-08-17 04:28:32.433987",
      "planned_duration": 240,
      "actual_start": null,
      "actual_end": null,
      "status": "PENDING",
      "success_criteria": [
        "Backtest completes successfully",
        "Results within 5% of expected (24.07% return)",
        "Trade log validation passed",
        "Risk management verified"
      ],
      "actual_results": {},
      "issues": [],
      "cost_impact": 0.0
    },
    {
      "id": "T1_M4_PAPER_TRADING",
      "track": "TRACK_1",
      "description": "Paper trading deployment + validation",
      "planned_start": "2025-08-17 08:28:32.433987",
      "planned_duration": 360,
      "actual_start": null,
      "actual_end": null,
      "status": "PENDING",
      "success_criteria": [
        "Paper trading deployed successfully",
        "Real-time data feeds active",
        "Signal generation functional",
        "Position management working"
      ],
      "actual_results": {},
      "issues": [],
      "cost_impact": 0.0
    },
    {
      "id": "T1_M5_MONITORING_SETUP",
      "track": "TRACK_1",
      "description": "Monitoring dashboard + alerts activation",
      "planned_start": "2025-08-17 14:28:32.433987",
      "planned_duration": 240,
      "actual_start": null,
      "actual_end": null,
      "status": "PENDING",
      "success_criteria": [
        "Real-time monitoring active",
        "Alert thresholds configured",
        "Performance tracking operational",
        "Daily reporting system ready"
      ],
      "actual_results": {},
      "issues": [],
      "cost_impact": 0.0
    },
    {
      "id": "T2_M1_ENVIRONMENT_SETUP",
      "track": "TRACK_2",
      "description": "Google Colab Pro + GPU environment",
      "planned_start": "2025-08-17 02:28:32.433987",
      "planned_duration": 30,
      "actual_start": "2025-08-17 02:28:32.435988",
      "actual_end": null,
      "status": "IN_PROGRESS",
      "success_criteria": [
        "Colab Pro subscription active",
        "GPU runtime available",
        "Basic dependencies installed"
      ],
      "actual_results": {},
      "issues": [],
      "cost_impact": 0.0
    },
    {
      "id": "T2_M2_MODEL_DEPLOYMENT",
      "track": "TRACK_2",
      "description": "FinBERT model download + testing",
      "planned_start": "2025-08-17 02:58:32.433987",
      "planned_duration": 90,
      "actual_start": null,
      "actual_end": null,
      "status": "PENDING",
      "success_criteria": [
        "FinBERT model loaded successfully",
        "GPU inference working",
        "Basic sentiment analysis functional"
      ],
      "actual_results": {},
      "issues": [],
      "cost_impact": 0.0
    },
    {
      "id": "T2_M3_PIPELINE_DEVELOPMENT",
      "track": "TRACK_2",
      "description": "Multi-asset sentiment pipeline",
      "planned_start": "2025-08-17 04:28:32.433987",
      "planned_duration": 120,
      "actual_start": null,
      "actual_end": null,
      "status": "PENDING",
      "success_criteria": [
        "5-asset processing capability",
        "Sentiment aggregation working",
        "Quality filtering implemented"
      ],
      "actual_results": {},
      "issues": [],
      "cost_impact": 0.0
    },
    {
      "id": "T2_M4_API_INTEGRATION",
      "track": "TRACK_2",
      "description": "Twitter/Reddit API configuration",
      "planned_start": "2025-08-17 06:28:32.433987",
      "planned_duration": 480,
      "actual_start": null,
      "actual_end": null,
      "status": "PENDING",
      "success_criteria": [
        "API credentials configured",
        "Data collection functional",
        "Rate limiting handled",
        "Real-time processing working"
      ],
      "actual_results": {},
      "issues": [],
      "cost_impact": 0.0
    },
    {
      "id": "T2_M5_INTEGRATION_PREP",
      "track": "TRACK_2",
      "description": "Sentiment-trading integration architecture",
      "planned_start": "2025-08-17 14:28:32.433987",
      "planned_duration": 360,
      "actual_start": null,
      "actual_end": null,
      "status": "PENDING",
      "success_criteria": [
        "Integration framework designed",
        "Signal enhancement logic tested",
        "Performance validation complete",
        "Deployment ready"
      ],
      "actual_results": {},
      "issues": [],
      "cost_impact": 0.0
    }
  ],
  "budget_items": [
    {
      "category": "TRACK_1",
      "description": "QuantConnect Account (Free)",
      "planned_cost": 0.0,
      "actual_cost": 0.0,
      "recurring": false,
      "timestamp": "2025-08-17 02:28:32.434988"
    },
    {
      "category": "TRACK_2",
      "description": "Google Colab Pro Subscription",
      "planned_cost": 10.0,
      "actual_cost": 10.0,
      "recurring": true,
      "timestamp": "2025-08-17 02:28:32.435988"
    }
  ],
  "reports": []
}